{
  "generated_at": "2026-01-21T08:55:25.497722+09:00",
  "field": "power",
  "field_label": "パワー半導体",
  "highlight": {
    "category": "重要トピック",
    "stars": 2,
    "title": "TDK Launches DC Link Film Capacitors",
    "summary": "The new DC link capacitors are optimized for SiC-based inverters requiring low inductances (ESL of 8 nH) and high-freque",
    "sources": [
      {
        "name": "powerelectronicsnews.com",
        "url": "https://www.powerelectronicsnews.com/tdk-launches-dc-link-film-capacitors"
      }
    ]
  },
  "sections": {
    "news": [
      {
        "title": "TDK Launches DC Link Film Capacitors",
        "blurb": "The new DC link capacitors are optimized for SiC-based inverters requiring low inductances (ESL of 8 nH) and high-freque",
        "category": "company",
        "date": "2026-01-20",
        "stars": 2,
        "source": {
          "name": "powerelectronicsnews.com",
          "url": "https://www.powerelectronicsnews.com/tdk-launches-dc-link-film-capacitors"
        },
        "field": {
          "primary": "power",
          "device": "power",
          "process": null,
          "market": null,
          "industry": null
        }
      },
      {
        "title": "ABB Re-enters the Solar Inverter Market through Gamesa Electric",
        "blurb": "ABB acquires Gamesa Electric’s power electronics business to capitalize on the maturing renewable energy sector. The pos",
        "category": "company",
        "date": "2026-01-20",
        "stars": 2,
        "source": {
          "name": "powerelectronicsnews.com",
          "url": "https://www.powerelectronicsnews.com/abb-re-enters-the-solar-inverter-market-through-gamesa-electric"
        },
        "field": {
          "primary": "power",
          "device": "power",
          "process": null,
          "market": null,
          "industry": null
        }
      }
    ],
    "tech": [],
    "market": []
  }
}