{
  "generated_at": "2026-01-22T21:51:55.062365+09:00",
  "highlight": {
    "category": "重要トピック",
    "stars": 3,
    "title": "Microchip Launches 600 V Gate Driver Lineup",
    "summary": "Microchipが600V対応の新型ゲートドライバを発表。高電圧電源ソリューションのラインナップを拡充。",
    "sources": [
      {
        "name": "powerelectronicsnews.com",
        "url": "https://www.powerelectronicsnews.com/microchip-launches-600-v-gate-driver-lineup"
      }
    ]
  },
  "sections": {
    "business": [
      {
        "title": "Every Atom Now Counts In Advanced Chip Manufacturing",
        "blurb": "AI時代向け半導体製造では、原子層堆積とハイブリッド誘電体が信頼性とスケーリングを再定義し、原子レベルでの精度が不可欠になっている。",
        "category": "business",
        "date": "2026-01-22",
        "stars": 3,
        "source": {
          "name": "semiengineering.com",
          "url": "https://semiengineering.com/every-atom-now-counts-in-advanced-chip-manufacturing"
        },
        "field": {
          "primary": "frontend",
          "device": null,
          "process": "frontend",
          "market": null,
          "industry": null
        }
      },
      {
        "title": "An Explosion In Interconnect Complexity",
        "blurb": "半導体業界では配線設計プラットフォームが2から5に増加し、複雑性が爆発的に増大している。",
        "category": "business",
        "date": "2026-01-22",
        "stars": 3,
        "source": {
          "name": "semiengineering.com",
          "url": "https://semiengineering.com/an-explosion-in-interconnect-complexity"
        },
        "field": {
          "primary": "general",
          "device": null,
          "process": null,
          "market": null,
          "industry": null
        }
      },
      {
        "title": "Oxides Bring Low Leakage Transistors To Leading-Edge Memories",
        "blurb": "DRAM不足とSRAMのスケーリング限界に対応するため、低リーク電流トランジスタの研究開発が活発化しています。",
        "category": "business",
        "date": "2026-01-22",
        "stars": 3,
        "source": {
          "name": "semiengineering.com",
          "url": "https://semiengineering.com/oxides-bring-low-leakage-transistors-to-leading-edge-memories"
        },
        "field": {
          "primary": "memory",
          "device": "memory",
          "process": null,
          "market": null,
          "industry": null
        }
      },
      {
        "title": "Ripple Effects: Why Water Risk Is The Next Major Business Challenge For The Semiconductor Industry",
        "blurb": "半導体工場の4割超が2030～2040年に高水ストレス地域に立地。水リスクが半導体業界の次なる事業課題となる。",
        "category": "business",
        "date": "2026-01-22",
        "stars": 3,
        "source": {
          "name": "semiengineering.com",
          "url": "https://semiengineering.com/ripple-effects-why-water-risk-is-the-next-major-business-challenge-for-the-semiconductor-industry"
        },
        "field": {
          "primary": "general",
          "device": null,
          "process": null,
          "market": null,
          "industry": null
        }
      },
      {
        "title": "Non-volatile Ferroelectric Silicon Photonics As A Scalable, Heat-free Platform For Energy-efficient Photonic Computing (UPV, iPronics et al.)",
        "blurb": "強誘電体シリコンフォトニクスによる、熱フリーで省電力な光コンピューティングプラットフォームが開発された。",
        "category": "business",
        "date": "2026-01-22",
        "stars": 3,
        "source": {
          "name": "semiengineering.com",
          "url": "https://semiengineering.com/non-volatile-ferroelectric-silicon-photonics-as-a-scalable-heat-free-platform-for-energy-efficient-photonic-computing-upv-ipronics-et-al"
        },
        "field": {
          "primary": "general",
          "device": null,
          "process": null,
          "market": null,
          "industry": null
        }
      },
      {
        "title": "ディスコの通期売上高、初の4000億円超へ 生成AI需要で",
        "blurb": "ディスコ、2025年度売上高4190億円で初の4000億円超えへ。生成AI向け半導体需要が牽引し、純利益も過去最高を更新する見込み。",
        "category": "business",
        "date": "2026-01-22",
        "stars": 3,
        "source": {
          "name": "itmedia.co.jp",
          "url": "https://eetimes.itmedia.co.jp/ee/articles/2601/22/news063.html"
        },
        "field": {
          "primary": "memory",
          "device": "memory",
          "process": null,
          "market": null,
          "industry": null
        }
      },
      {
        "title": "Can Open-Source ISAs Catalyze Smart Manufacturing?",
        "blurb": "IoTはスマート製造に不可欠。オープンソースISAが、製造業のデータ活用と効率化を促進する可能性。",
        "category": "business",
        "date": "2026-01-22",
        "stars": 3,
        "source": {
          "name": "embedded.com",
          "url": "https://www.embedded.com/can-open-source-isas-catalyze-smart-manufacturing"
        },
        "field": {
          "primary": "industrial",
          "device": null,
          "process": null,
          "market": "industrial",
          "industry": null
        }
      }
    ],
    "tools": [
      {
        "title": "Exploring SiC MOSFET Architectures, Part 1",
        "blurb": "SiC MOSFETのアーキテクチャ、特性、利点、設計上の考慮事項について解説するシリーズの第1部。",
        "category": "tools",
        "date": "2026-01-22",
        "stars": 3,
        "source": {
          "name": "powerelectronicsnews.com",
          "url": "https://www.powerelectronicsnews.com/exploring-sic-mosfet-architectures-part-1"
        },
        "field": {
          "primary": "power",
          "device": "power",
          "process": null,
          "market": null,
          "industry": null
        }
      },
      {
        "title": "A Novel Side-channel Attack That Utilizes Memory Re-orderings (U. of Washington, Duke, UCSC et al.)",
        "blurb": "メモリ操作の並べ替えを利用した新たなサイドチャネル攻撃「Memory DisOrder」が発表された。効率向上のため多くの並列処理ユニットで採用されている。",
        "category": "tools",
        "date": "2026-01-22",
        "stars": 3,
        "source": {
          "name": "semiengineering.com",
          "url": "https://semiengineering.com/a-novel-side-channel-attack-that-utilizes-memory-re-orderings-u-of-washington-duke-ucsc-et-al"
        },
        "field": {
          "primary": "general",
          "device": null,
          "process": null,
          "market": null,
          "industry": null
        }
      },
      {
        "title": "市場は低成長でも中身は超進化！ 最新スマートウォッチを分解",
        "blurb": "市場は低成長でもスマートウォッチは毎年進化。2025年発売モデルの機能・性能アップを分解して解説。",
        "category": "tools",
        "date": "2026-01-22",
        "stars": 3,
        "source": {
          "name": "itmedia.co.jp",
          "url": "https://eetimes.itmedia.co.jp/ee/articles/2601/22/news017.html"
        },
        "field": null
      },
      {
        "title": "Syslogic Unveils GNSS Expansion Board",
        "blurb": "Syslogicが産業用途向け高精度GNSS拡張ボードを発表。自律走行農機や建設機械、AGV/AMRの精密誘導に対応。",
        "category": "tools",
        "date": "2026-01-22",
        "stars": 3,
        "source": {
          "name": "embedded.com",
          "url": "https://www.embedded.com/syslogic-unveils-gnss-expansion-board"
        },
        "field": {
          "primary": "automotive",
          "device": null,
          "process": null,
          "market": "automotive",
          "industry": null
        }
      }
    ],
    "company": [
      {
        "title": "Microchip Launches 600 V Gate Driver Lineup",
        "blurb": "Microchipが600V対応の新型ゲートドライバを発表。高電圧電源ソリューションのラインナップを拡充。",
        "category": "company",
        "date": "2026-01-22",
        "stars": 3,
        "source": {
          "name": "powerelectronicsnews.com",
          "url": "https://www.powerelectronicsnews.com/microchip-launches-600-v-gate-driver-lineup"
        },
        "field": {
          "primary": "power",
          "device": "power",
          "process": null,
          "market": null,
          "industry": null
        }
      },
      {
        "title": "Scaling of 2D Semiconductor Nanoribbons for High Performance Transistors (Purdue, NUS et al.)",
        "blurb": "2次元半導体ナノリボンを用いた高性能トランジスタに関する論文が発表された。将来のGAAナノリボン構造への応用が期待される。",
        "category": "company",
        "date": "2026-01-22",
        "stars": 3,
        "source": {
          "name": "semiengineering.com",
          "url": "https://semiengineering.com/scaling-of-2d-semiconductor-nanoribbons-for-high-performance-transistors-purdue-nus-et-al"
        },
        "field": {
          "primary": "miniaturization",
          "device": null,
          "process": "miniaturization",
          "market": null,
          "industry": null
        }
      },
      {
        "title": "Co-optimization Approaches For Reliable and Efficient AI Acceleration (Peking University et al.)",
        "blurb": "北京大学などの研究者が、AIアクセラレータの信頼性と効率を高めるための新しい技術論文を発表しました。CMOS技術の微細化に伴う信頼性課題に対処します。",
        "category": "company",
        "date": "2026-01-22",
        "stars": 3,
        "source": {
          "name": "semiengineering.com",
          "url": "https://semiengineering.com/co-optimization-approaches-for-reliable-and-efficient-ai-acceleration-peking-university-et-al"
        },
        "field": {
          "primary": "general",
          "device": null,
          "process": null,
          "market": null,
          "industry": null
        }
      },
      {
        "title": "TSMCでも足りないAI需要　Rapidusにチャンスか",
        "blurb": "AI需要が旺盛でTSMCでも不足。日本のRapidusに競合企業としての参入機会があるか注目される。",
        "category": "company",
        "date": "2026-01-22",
        "stars": 3,
        "source": {
          "name": "itmedia.co.jp",
          "url": "https://eetimes.itmedia.co.jp/ee/articles/2601/23/news019.html"
        },
        "field": {
          "primary": "ai",
          "device": null,
          "process": null,
          "market": "ai",
          "industry": null
        }
      },
      {
        "title": "0.2mm厚の高電圧対応絶縁シート開発、住友ベーク",
        "blurb": "住友ベークライトが厚さ0.2mmで耐トラッキング性に優れた絶縁シートを開発。xEVや産業機器の高電圧部品向け。",
        "category": "company",
        "date": "2026-01-22",
        "stars": 3,
        "source": {
          "name": "itmedia.co.jp",
          "url": "https://eetimes.itmedia.co.jp/ee/articles/2601/22/news036.html"
        },
        "field": {
          "primary": "power",
          "device": "power",
          "process": null,
          "market": "automotive",
          "industry": null
        }
      },
      {
        "title": "ER電池とサイズ互換の全固体電池モジュール、マクセル",
        "blurb": "マクセルがER電池とサイズ互換の全固体電池モジュールを開発。出力電圧3.6V、標準容量35mAh。",
        "category": "company",
        "date": "2026-01-22",
        "stars": 3,
        "source": {
          "name": "itmedia.co.jp",
          "url": "https://eetimes.itmedia.co.jp/ee/articles/2601/22/news035.html"
        },
        "field": null
      },
      {
        "title": "ボッシュ共同開発のSiC車載モジュール、富士電機が見本展示",
        "blurb": "富士電機はボッシュと共同開発したxEV向けSiCパワー半導体モジュール「M688」の見本を展示した。",
        "category": "company",
        "date": "2026-01-22",
        "stars": 3,
        "source": {
          "name": "itmedia.co.jp",
          "url": "https://eetimes.itmedia.co.jp/ee/articles/2601/22/news055.html"
        },
        "field": {
          "primary": "power",
          "device": "power",
          "process": null,
          "market": "automotive",
          "industry": null
        }
      },
      {
        "title": "映像が「宙に浮く」ディスプレイ　厚さ1ミリのメタレンズで実現",
        "blurb": "京セラは厚さ1mmのメタレンズで映像が宙に浮いて見えるスマートウォッチ型空中ディスプレイのプロトタイプをCES 2026で展示した。",
        "category": "company",
        "date": "2026-01-22",
        "stars": 3,
        "source": {
          "name": "itmedia.co.jp",
          "url": "https://eetimes.itmedia.co.jp/ee/articles/2601/22/news066.html"
        },
        "field": null
      }
    ],
    "sns": []
  }
}