{
  "generated_at": "2026-01-31T06:09:04.578806+09:00",
  "highlight": {
    "category": "重要トピック",
    "stars": 3,
    "title": "GaN-on-Si Substrates, QSPICE Circuit Diagram Editor, 300mm GaN Adoption: Power Electronics Week Insights",
    "summary": "パワーエレクトロニクスウィークでは、GaN-on-Si基板、QSPICE回路図エディタ、300mm GaN採用の最新動向が紹介された。",
    "sources": [
      {
        "name": "powerelectronicsnews.com",
        "url": "https://www.powerelectronicsnews.com/gan-on-si-substrates-qspice-circuit-diagram-editor-300mm-gan-adoption-power-electronics-week-insights"
      }
    ]
  },
  "sections": {
    "business": [
      {
        "title": "Wide Bandgap Monthly Insights – January 2026",
        "blurb": "2026年1月の広帯域ギャップ材料（SiC、GaN）に関する最新ニュースをまとめた記事。",
        "category": "business",
        "date": "2026-01-30",
        "stars": 3,
        "source": {
          "name": "powerelectronicsnews.com",
          "url": "https://www.powerelectronicsnews.com/wide-bandgap-monthly-insights-january-2026"
        },
        "field": {
          "primary": "power",
          "device": "power",
          "process": null,
          "market": null,
          "industry": null
        }
      },
      {
        "title": "Chip Industry Week In Review",
        "blurb": "半導体業界の最新動向：高速インターコネクト新合弁、インドの2nmチップ、NAND増強、AIチップ、新工場、AI人材育成など。",
        "category": "business",
        "date": "2026-01-30",
        "stars": 3,
        "source": {
          "name": "semiengineering.com",
          "url": "https://semiengineering.com/chip-industry-week-in-review-123"
        },
        "field": {
          "primary": "memory",
          "device": "memory",
          "process": "miniaturization",
          "market": "ai",
          "industry": null
        }
      },
      {
        "title": "2025年の半導体業界を振り返る",
        "blurb": "2025年は生成AI普及とヒューマノイドロボット発表が相次ぎ、半導体業界は不透明な世界経済の中、活況を呈した。",
        "category": "business",
        "date": "2026-01-30",
        "stars": 3,
        "source": {
          "name": "itmedia.co.jp",
          "url": "https://eetimes.itmedia.co.jp/ee/articles/2601/30/news001.html"
        },
        "field": {
          "primary": "general",
          "device": null,
          "process": null,
          "market": null,
          "industry": null
        }
      },
      {
        "title": "XConn買収で見えたMarvellの狙い、AIインターコネクトに本格参戦",
        "blurb": "MarvellがXConn買収でAIインターコネクトに本格参戦。データセンター向け次世代技術競争の幕開け。",
        "category": "business",
        "date": "2026-01-30",
        "stars": 3,
        "source": {
          "name": "itmedia.co.jp",
          "url": "https://eetimes.itmedia.co.jp/ee/articles/2601/30/news069.html"
        },
        "field": {
          "primary": "datacenter",
          "device": null,
          "process": null,
          "market": "datacenter",
          "industry": null
        }
      },
      {
        "title": "「AI需要は持続的なもの」　ASML、25年Q4の売上高は過去最高",
        "blurb": "半導体露光装置メーカーASMLの25年Q4売上高は過去最高を記録。AI需要の持続性を背景に、通期業績も堅調だった。",
        "category": "business",
        "date": "2026-01-30",
        "stars": 3,
        "source": {
          "name": "itmedia.co.jp",
          "url": "https://eetimes.itmedia.co.jp/ee/articles/2601/30/news060.html"
        },
        "field": null
      },
      {
        "title": "CES2026: Snapdragon X2 Plus 3nm SoCs Targets Copilot+ PCs With 80 TOPS AI and Multi-Day Battery",
        "blurb": "CES2026で発表されたSnapdragon X2 Plusは、3nmプロセス、80TOPSのAI性能、数日間のバッテリー寿命を持つCopilot+ PC向け新SoC。",
        "category": "business",
        "date": "2026-01-30",
        "stars": 3,
        "source": {
          "name": "electronics-lab.com",
          "url": "https://www.electronics-lab.com/ces2026-snapdragon-x2-plus-3nm-socs-targets-copilot-pcs-with-80-tops-ai-and-multi-day-battery"
        },
        "field": {
          "primary": "logic",
          "device": "logic",
          "process": "miniaturization",
          "market": null,
          "industry": null
        }
      },
      {
        "title": "Cheap Chinese EVs Are Hitting Canada. For The U.S., 'A Matter Of When'",
        "blurb": "中国製EVがカナダに上陸。米国への影響は時間の問題と見られる。自動運転関連のニュースも。",
        "category": "business",
        "date": "2026-01-30",
        "stars": 3,
        "source": {
          "name": "insideevs.com",
          "url": "https://insideevs.com/news/785906/chinese-evs-mexico-canada-usa"
        },
        "field": null
      },
      {
        "title": "Used EVs Are The Cheapest Cars To Own: Study",
        "blurb": "中古EVは新車・中古ガソリン車を上回り、最も所有コストが低いことが研究で判明しました。",
        "category": "business",
        "date": "2026-01-30",
        "stars": 3,
        "source": {
          "name": "insideevs.com",
          "url": "https://insideevs.com/news/785921/used-evs-cheapest-cost-ownership-study"
        },
        "field": null
      },
      {
        "title": "GaN-on-Si Substrates, QSPICE Circuit Diagram Editor, 300mm GaN Adoption: Power Electronics Week Insights",
        "blurb": "パワーエレクトロニクスウィークでは、GaN-on-Si基板、QSPICE回路図エディタ、300mm GaN採用の最新動向が紹介された。",
        "category": "business",
        "date": "2026-01-31",
        "stars": 3,
        "source": {
          "name": "powerelectronicsnews.com",
          "url": "https://www.powerelectronicsnews.com/gan-on-si-substrates-qspice-circuit-diagram-editor-300mm-gan-adoption-power-electronics-week-insights"
        },
        "field": {
          "primary": "power",
          "device": "power",
          "process": null,
          "market": null,
          "industry": null
        }
      },
      {
        "title": "600-V MOSFET enables efficient, reliable power conversion",
        "blurb": "AOSが600V耐圧のNチャネルMOSFET「AOTL037V60DE2」を発表。高効率・高信頼性の電力変換を実現。",
        "category": "business",
        "date": "2026-01-31",
        "stars": 3,
        "source": {
          "name": "edn.com",
          "url": "https://www.edn.com/600-v-mosfet-enables-efficient-reliable-power-conversion"
        },
        "field": {
          "primary": "power",
          "device": "power",
          "process": null,
          "market": null,
          "industry": null
        }
      },
      {
        "title": "1200-V SiC modules enable direct upgrades",
        "blurb": "ヴィーシェイは、競合製品と直接置き換え可能な1200V SiCパワーモジュール5種を発表しました。",
        "category": "business",
        "date": "2026-01-31",
        "stars": 3,
        "source": {
          "name": "edn.com",
          "url": "https://www.edn.com/1200-v-sic-modules-enable-direct-upgrades"
        },
        "field": {
          "primary": "power",
          "device": "power",
          "process": null,
          "market": null,
          "industry": null
        }
      },
      {
        "title": "Volvo's CEO Thinks The U.S. Market Is 'Perfect' For EVs. He Has A Point",
        "blurb": "ボルボCEOは米国市場がEVに最適だと考えている。欧州より米国の方がEV化しやすいという見解を示した。",
        "category": "business",
        "date": "2026-01-31",
        "stars": 3,
        "source": {
          "name": "insideevs.com",
          "url": "https://insideevs.com/news/785878/volvo-ceo-us-ev-strategy"
        },
        "field": null
      }
    ],
    "tools": [
      {
        "title": "Keysight automates complex coexistence testing",
        "blurb": "Keysightは、混雑したRF環境での無線デバイス性能検証を自動化するプラットフォームを発表しました。",
        "category": "tools",
        "date": "2026-01-31",
        "stars": 3,
        "source": {
          "name": "edn.com",
          "url": "https://www.edn.com/keysight-automates-complex-coexistence-testing"
        },
        "field": null
      },
      {
        "title": "Software-Defined Factories, AI Accelerators, Touch Controllers: Embedded Week Insights",
        "blurb": "組み込み技術の最新動向。ソフトウェア定義型工場、AIアクセラレータ、タッチコントローラに関する記事をまとめた。",
        "category": "tools",
        "date": "2026-01-31",
        "stars": 3,
        "source": {
          "name": "embedded.com",
          "url": "https://www.embedded.com/software-defined-factories-ai-accelerators-touch-controllers-embedded-week-insights"
        },
        "field": {
          "primary": "logic",
          "device": "logic",
          "process": null,
          "market": null,
          "industry": null
        }
      }
    ],
    "company": [
      {
        "title": "ROHM Unveils BD9xxN5 Series of LDO Regulators",
        "blurb": "ROHMは、出力電流500mAの新型LDOレギュレータ「BD9xxN5シリーズ」を発表しました。",
        "category": "company",
        "date": "2026-01-30",
        "stars": 3,
        "source": {
          "name": "powerelectronicsnews.com",
          "url": "https://www.powerelectronicsnews.com/rohm-unveils-bd9xxn5-series-of-ldo-regulators"
        },
        "field": null
      },
      {
        "title": "Impact Of The Film Transfer And Grain Size On The Cu-barrier Properties Of 2D WS2 Films (NUS et al.)",
        "blurb": "NUS等の研究者、2D WS2膜の銅バリア特性にフィルム転写と結晶粒径が与える影響を発表。微細電子デバイスへの応用が期待。",
        "category": "company",
        "date": "2026-01-30",
        "stars": 3,
        "source": {
          "name": "semiengineering.com",
          "url": "https://semiengineering.com/impact-of-the-film-transfer-and-grain-size-on-the-cu-barrier-properties-of-2d-ws2-films-nus-et-al"
        },
        "field": {
          "primary": "general",
          "device": null,
          "process": null,
          "market": null,
          "industry": null
        }
      },
      {
        "title": "有機半導体薄膜の多形転移を解明、京都大学ら",
        "blurb": "京大とグラーツ工科大は有機半導体薄膜の構造を分子レベルで解明。単分子膜相と薄膜相を区別して識別することに成功した。",
        "category": "company",
        "date": "2026-01-30",
        "stars": 3,
        "source": {
          "name": "itmedia.co.jp",
          "url": "https://eetimes.itmedia.co.jp/ee/articles/2601/30/news047.html"
        },
        "field": {
          "primary": "general",
          "device": null,
          "process": null,
          "market": null,
          "industry": null
        }
      },
      {
        "title": "モノリシック集積の限界を超えるヘテロジニアス集積化",
        "blurb": "TSMCはIEDMで、モノリシック集積の限界を超えるヘテロジニアス集積化技術の進化について講演した。",
        "category": "company",
        "date": "2026-01-30",
        "stars": 3,
        "source": {
          "name": "itmedia.co.jp",
          "url": "https://eetimes.itmedia.co.jp/ee/articles/2601/30/news036.html"
        },
        "field": null
      },
      {
        "title": "高配向性熱分解グラファイトの自己復元特性を確認、三菱電機ら",
        "blurb": "三菱電機と京大は、高配向性熱分解グラファイトの自己復元特性を初確認。MEMSの長寿命化と信頼性向上に貢献。",
        "category": "company",
        "date": "2026-01-30",
        "stars": 3,
        "source": {
          "name": "itmedia.co.jp",
          "url": "https://eetimes.itmedia.co.jp/ee/articles/2601/30/news046.html"
        },
        "field": null
      },
      {
        "title": "AI時代のニーズ捉え開発加速、キオクシア次期社長の展望",
        "blurb": "キオクシアHDは早坂社長が退任し、太田副社長が新社長に就任。AI時代のニーズ捉え開発加速へ。",
        "category": "company",
        "date": "2026-01-30",
        "stars": 3,
        "source": {
          "name": "itmedia.co.jp",
          "url": "https://eetimes.itmedia.co.jp/ee/articles/2601/30/news064.html"
        },
        "field": null
      },
      {
        "title": "Chandra X-Ray Mirror",
        "blurb": "チャンドラX線観測衛星の仕組みと、予算削減による研究停止の悲報を伝える記事。",
        "category": "company",
        "date": "2026-01-30",
        "stars": 3,
        "source": {
          "name": "edn.com",
          "url": "https://www.edn.com/chandra-x-ray-mirror"
        },
        "field": null
      },
      {
        "title": "Mikroe and Renesas Partner on MCU Development Tools",
        "blurb": "MikroeとRenesasがMCU開発ツールで提携。MikroeはRenesasの多数のMCUに対応した開発ツールを提供する。",
        "category": "company",
        "date": "2026-01-30",
        "stars": 3,
        "source": {
          "name": "embedded.com",
          "url": "https://www.embedded.com/mikroe-and-renesas-partner-on-mcu-development-tools"
        },
        "field": null
      },
      {
        "title": "Rohm Launches LDO Regulator Series With Ultra-Stable Control Technology",
        "blurb": "ロームは、車載・産業・民生用途向けに、低消費電力・高安定性制御技術搭載のLDOレギュレータ新シリーズを発売。",
        "category": "company",
        "date": "2026-01-30",
        "stars": 3,
        "source": {
          "name": "electronics-lab.com",
          "url": "https://www.electronics-lab.com/rohm-launches-ldo-regulator-series-with-ultra-stable-control-technology"
        },
        "field": {
          "primary": "industrial",
          "device": null,
          "process": null,
          "market": "industrial",
          "industry": null
        }
      },
      {
        "title": "Scout Didn't Expect This: Nearly All Of Its 'Electric' Truck Buyers Want A Gas Engine",
        "blurb": "Scout社のEVトラック、予約者のほぼ全員がレンジエクステンダー付きガソリンエンジンを希望。CEOも想定外の需要。",
        "category": "company",
        "date": "2026-01-30",
        "stars": 3,
        "source": {
          "name": "insideevs.com",
          "url": "https://insideevs.com/news/785904/scout-erev-harvester-reservations-ceo-expectations"
        },
        "field": null
      },
      {
        "title": "The 2027 Acura RSX: Everything We Know",
        "blurb": "アキュラはGM開発のZDXを廃止し、自社開発の新型EV「RSX」を2027年に投入する。",
        "category": "company",
        "date": "2026-01-30",
        "stars": 3,
        "source": {
          "name": "insideevs.com",
          "url": "https://insideevs.com/reviews/785703/acura-rsx-ev-everything-we-know"
        },
        "field": {
          "primary": "automotive",
          "device": null,
          "process": null,
          "market": "automotive",
          "industry": null
        }
      },
      {
        "title": "Touch ICs scale across automotive display sizes",
        "blurb": "マイクロチップ、車載ディスプレイ向けタッチICを発表。多様なサイズに対応し、製品ラインアップを拡充。",
        "category": "company",
        "date": "2026-01-31",
        "stars": 3,
        "source": {
          "name": "edn.com",
          "url": "https://www.edn.com/touch-ics-scale-across-automotive-display-sizes"
        },
        "field": null
      },
      {
        "title": "Stable LDOs use small-output caps",
        "blurb": "ロームのナノキャップ技術搭載LDOレギュレータIC「BD9xxN5」シリーズは、500mA出力で小型出力コンデンサでも安定動作。",
        "category": "company",
        "date": "2026-01-31",
        "stars": 3,
        "source": {
          "name": "edn.com",
          "url": "https://www.edn.com/stable-ldos-use-small-output-caps"
        },
        "field": null
      },
      {
        "title": "The Tesla Model S Is Dead. Here's Why It Mattered",
        "blurb": "テスラ初のEVセダン、モデルSが生産終了。EV市場におけるその功績と影響を振り返る。",
        "category": "company",
        "date": "2026-01-31",
        "stars": 3,
        "source": {
          "name": "insideevs.com",
          "url": "https://insideevs.com/features/785976/tesla-model-s-ev-charging-podcast"
        },
        "field": null
      }
    ],
    "sns": []
  }
}